ndx_multisubjects/spec/ndx-multisubjects.extensions.yaml
ndx_multisubjects/spec/ndx-multisubjects.namespace.yaml
ndx_multisubjects/__init__.py
ndx_multisubjects/ndx_multisubjects.py
ndx_multisubjects/ndx_multisubjects_nwb_file_io.py
ndx_multisubjects-0.1.0.dist-info/METADATA
ndx_multisubjects-0.1.0.dist-info/WHEEL
ndx_multisubjects-0.1.0.dist-info/licenses/LICENSE.txt
ndx_multisubjects-0.1.0.dist-info/RECORD
