Metadata-Version: 2.4
Name: ndx-multisubjects
Version: 0.1.0
Summary: Allow for multiple subjects to be represented in a single nwb file. This is for experiments where subjects are being recorded at the same time in the same session.
Project-URL: Homepage, https://github.com/nehatk17/ndx-multisubjects
Project-URL: Bug Tracker, https://github.com/nehatk17/ndx-multisubjects/issues
Project-URL: Changelog, https://github.com/nehatk17/ndx-multisubjects/blob/main/CHANGELOG.md
Author-email: Neha Thomas <neha.thomas@jhuapl.edu>, Ryan Ly <rly@lbl.gov>
License: BSD-3-Clause
License-File: LICENSE.txt
Keywords: NWB,NeurodataWithoutBorders,ndx-extension,nwb-extension
Classifier: Development Status :: 4 - Beta
Classifier: Intended Audience :: Developers
Classifier: Intended Audience :: Science/Research
Classifier: License :: OSI Approved :: BSD License
Classifier: Programming Language :: Python
Classifier: Programming Language :: Python :: 3.9
Classifier: Programming Language :: Python :: 3.10
Classifier: Programming Language :: Python :: 3.11
Classifier: Programming Language :: Python :: 3.12
Classifier: Programming Language :: Python :: 3.13
Requires-Python: >=3.9
Requires-Dist: hdmf>=3.14.1
Requires-Dist: pynwb>=2.8.0
Provides-Extra: dev
Requires-Dist: black>=24.4.2; extra == 'dev'
Requires-Dist: codespell>=2.3.0; extra == 'dev'
Requires-Dist: coverage>=7.5.4; extra == 'dev'
Requires-Dist: hdmf-docutils>=0.4.7; extra == 'dev'
Requires-Dist: pre-commit>=3.5.0; extra == 'dev'
Requires-Dist: pytest-cov>=5.0.0; extra == 'dev'
Requires-Dist: pytest-subtests>=0.12.1; extra == 'dev'
Requires-Dist: pytest>=8.2.2; extra == 'dev'
Requires-Dist: python-dateutil>=2.8.2; extra == 'dev'
Requires-Dist: ruff>=0.4.10; extra == 'dev'
Provides-Extra: docs
Requires-Dist: hdmf-docutils>=0.4.7; extra == 'docs'
Provides-Extra: min-reqs
Requires-Dist: hdmf==3.14.1; extra == 'min-reqs'
Requires-Dist: pynwb==2.8.0; extra == 'min-reqs'
Provides-Extra: test
Requires-Dist: coverage>=7.5.4; extra == 'test'
Requires-Dist: pytest-cov>=5.0.0; extra == 'test'
Requires-Dist: pytest-subtests>=0.12.1; extra == 'test'
Requires-Dist: pytest>=8.2.2; extra == 'test'
Requires-Dist: python-dateutil>=2.8.2; extra == 'test'
